<?xml version="1.0" encoding="UTF-8"?>
<AliceModel creationYear="2011" creator="Laura Paoletti" name="MadHatter">
    <BoundingBox>
        <Min x="-0.3020360469818115" y="-0.0018274927278980613" z="-0.18732349574565887"/>
        <Max x="0.3020360469818115" y="1.9300282001495361" z="0.6507742404937744"/>
    </BoundingBox>
    <Tags>
        <Tag>wonderland</Tag>
        <Tag>alice</Tag>
    </Tags>
    <GroupTags>
        <GroupTag>characters</GroupTag>
    </GroupTags>
    <ThemeTags>
        <ThemeTag>*wonderland</ThemeTag>
    </ThemeTags>
    <Resource modelName="MadHatter" resourceName="DEFAULT" textureName="DEFAULT"/>
</AliceModel>
